instagram_reels/__init__.py
instagram_reels/api/__init__.py
instagram_reels/api/private/__init__.py
instagram_reels/api/private/client/MediaInfoClient.py
instagram_reels/api/private/client/ReelsClient.py
instagram_reels/api/private/client/__init__.py
instagram_reels/api/private/parser/MediaInfoParser.py
instagram_reels/api/private/parser/__init__.py
instagram_reels/api/private/service/MediaInfoService.py
instagram_reels/api/private/service/__init__.py
instagram_reels/api/public/__init__.py
instagram_reels/api/public/client/MediaInfoClient.py
instagram_reels/api/public/client/ReelsClient.py
instagram_reels/api/public/client/__init__.py
instagram_reels/api/public/model/InstagramSettingDataClass.py
instagram_reels/api/public/model/InstagramSettingsParamsDataClass.py
instagram_reels/api/public/model/__init__.py
instagram_reels/api/public/parser/MediaInfoParser.py
instagram_reels/api/public/parser/__init__.py
instagram_reels/api/public/service/CrossSiteRequestTokenService.py
instagram_reels/api/public/service/DynamicTokenService.py
instagram_reels/api/public/service/InstagramApiParamsService.py
instagram_reels/api/public/service/__init__.py
instagram_reels/api/public/util/BitMapUtil.py
instagram_reels/api/public/util/__init__.py
instagram_reels/common/IReelsClient.py
instagram_reels/common/JsonParser.py
instagram_reels/common/__init__.py
instagram_reels/common/model/InstagramShortUser.py
instagram_reels/common/model/ReelAuthor.py
instagram_reels/common/model/ReelModel.py
instagram_reels/common/model/ReelPreview.py
instagram_reels/common/model/ReelVideo.py
instagram_reels/common/model/__init__.py
instagram_reels/main/InstagramAPIClient.py
instagram_reels/main/InstagramAPIClientImpl.py
instagram_reels/main/__init__.py
instagram_reels/reels/__init__.py
instagram_reels-0.2.4.dist-info/LICENSE
instagram_reels-0.2.4.dist-info/METADATA
instagram_reels-0.2.4.dist-info/WHEEL
instagram_reels-0.2.4.dist-info/RECORD
