Metadata-Version: 2.3
Name: instagram-reels
Version: 0.2.4
Summary: Instagram Reels Downloader
Author: Николай Витальевич Никоноров
Author-email: nnv@bitt.moe
Requires-Python: >=3.10,<4.0
Classifier: Programming Language :: Python :: 3
Classifier: Programming Language :: Python :: 3.10
Classifier: Programming Language :: Python :: 3.11
Classifier: Programming Language :: Python :: 3.12
Classifier: Programming Language :: Python :: 3.13
Requires-Dist: aiohttp (>=3.8.3,<4.0.0)
Requires-Dist: aiosignal (>=1.3.1,<2.0.0)
Requires-Dist: async-timeout (>=4.0.2,<5.0.0)
Requires-Dist: attrs (>=22.2.0,<23.0.0)
Requires-Dist: beautifulsoup4 (>=4.11.2,<5.0.0)
Requires-Dist: charset-normalizer (>=2.1.1,<3.0.0)
Requires-Dist: frozenlist (>=1.3.3,<2.0.0)
Requires-Dist: idna (>=3.4,<4.0)
Requires-Dist: instagram-auth (>=0.1.1,<0.2.0)
Requires-Dist: multidict (>=6.0.4,<7.0.0)
Requires-Dist: soupsieve (>=2.3.2.post1,<3.0.0)
Requires-Dist: yarl (>=1.8.2,<2.0.0)
Project-URL: Repository, https://gitlab.com/bitt_moe/instagram/reels_downloader
